{
  "report_type": "ddos",
  "group_name": "NoName057(16)",
  "actor_name": "NoName057(16)",
  "operation_name": "",
  "network": "unknown",
  "targeted_website": "https://land-net.taitung.gov.tw/info.php",
  "targeted_org": "",
  "attack_type": "DDoS",
  "attacked_country": "TW",
  "attacker_country_affiliation": "unknown",
  "attack_date": "2025-03-18",
  "check_host": "2421aaa6keec",
  "additional_image": "",
  "check_details": {
    "website_verification": "https://land-net.taitung.gov.tw/info.php",
    "check_date": "2025-03-18",
    "check_results": {
      "bg1.node.check-host.net": [
        [
          0,
          3.00332188606262,
          "Connection timed out",
          null,
          null
        ]
      ],
      "br1.node.check-host.net": [
        [
          0,
          3.00200510025024,
          "Connection timed out",
          null,
          null
        ]
      ],
      "ch1.node.check-host.net": [
        [
          0,
          3.00179004669189,
          "Connection timed out",
          null,
          null
        ]
      ],
      "cz1.node.check-host.net": [
        [
          0,
          3.00186204910278,
          "Connection timed out",
          null,
          null
        ]
      ],
      "de1.node.check-host.net": [
        [
          0,
          3.00114393234253,
          "Connection timed out",
          null,
          null
        ]
      ],
      "de4.node.check-host.net": [
        [
          0,
          25.0010690689087,
          "Connection timed out",
          null,
          "60.248.62.203"
        ]
      ],
      "es1.node.check-host.net": [
        [
          0,
          25.0001320838928,
          "Connection timed out",
          null,
          "60.248.62.203"
        ]
      ],
      "fi1.node.check-host.net": [
        [
          0,
          25.0008502006531,
          "Connection timed out",
          null,
          "60.248.62.203"
        ]
      ],
      "fr1.node.check-host.net": [
        [
          0,
          3.00137400627136,
          "Connection timed out",
          null,
          null
        ]
      ],
      "fr2.node.check-host.net": [
        [
          0,
          0.00175189971923828,
          "Too many open files",
          null,
          null
        ]
      ],
      "hk1.node.check-host.net": [
        [
          0,
          3.0039439201355,
          "Connection timed out",
          null,
          null
        ]
      ],
      "hu1.node.check-host.net": [
        [
          0,
          24.9999258518219,
          "Connection timed out",
          null,
          "60.248.62.203"
        ]
      ],
      "id2.node.check-host.net": [
        [
          0,
          11.2873589992523,
          "Connection reset by peer",
          null,
          "60.248.62.203"
        ]
      ],
      "il1.node.check-host.net": [
        [
          0,
          3.00124001502991,
          "Connection timed out",
          null,
          null
        ]
      ],
      "il2.node.check-host.net": [
        [
          0,
          3.0017249584198,
          "Connection timed out",
          null,
          null
        ]
      ],
      "in1.node.check-host.net": [
        [
          0,
          2.00189185142517,
          "Connection reset by peer",
          null,
          "60.248.62.203"
        ]
      ],
      "ir1.node.check-host.net": [
        [
          0,
          3.00163793563843,
          "Connection timed out",
          null,
          null
        ]
      ],
      "ir2.node.check-host.net": [
        [
          0,
          25.0003139972687,
          "Connection timed out",
          null,
          "60.248.62.203"
        ]
      ],
      "ir3.node.check-host.net": [
        [
          0,
          3.00407409667969,
          "Connection timed out",
          null,
          null
        ]
      ],
      "ir5.node.check-host.net": [
        [
          0,
          3.00255799293518,
          "Connection timed out",
          null,
          null
        ]
      ],
      "ir6.node.check-host.net": [
        [
          0,
          3.00190782546997,
          "Connection timed out",
          null,
          null
        ]
      ],
      "it2.node.check-host.net": [
        [
          0,
          3.00163102149963,
          "Connection timed out",
          null,
          null
        ]
      ],
      "jp1.node.check-host.net": [
        [
          0,
          3.00169396400452,
          "Connection timed out",
          null,
          null
        ]
      ],
      "kz1.node.check-host.net": [
        [
          0,
          3.07821011543274,
          "Connection timed out",
          null,
          null
        ]
      ],
      "lt1.node.check-host.net": [
        [
          0,
          3.00193095207214,
          "Connection timed out",
          null,
          null
        ]
      ],
      "md1.node.check-host.net": [
        [
          0,
          3.00225901603699,
          "Connection timed out",
          null,
          null
        ]
      ],
      "nl1.node.check-host.net": [
        [
          0,
          3.00096607208252,
          "Connection timed out",
          null,
          null
        ]
      ],
      "nl2.node.check-host.net": [
        [
          0,
          3.00203204154968,
          "Connection timed out",
          null,
          null
        ]
      ],
      "pl1.node.check-host.net": [
        [
          0,
          24.9994730949402,
          "Connection timed out",
          null,
          "60.248.62.203"
        ]
      ],
      "pl2.node.check-host.net": [
        [
          0,
          10.7982168197632,
          "Connection reset by peer",
          null,
          "60.248.62.203"
        ]
      ],
      "pt1.node.check-host.net": [
        [
          0,
          3.00116801261902,
          "Connection timed out",
          null,
          null
        ]
      ],
      "rs1.node.check-host.net": [
        [
          0,
          3.00202798843384,
          "Connection timed out",
          null,
          null
        ]
      ],
      "ru1.node.check-host.net": [
        [
          0,
          3.00131988525391,
          "Connection timed out",
          null,
          null
        ]
      ],
      "ru2.node.check-host.net": [
        [
          0,
          8.97858190536499,
          "Connection reset by peer",
          null,
          "60.248.62.203"
        ]
      ],
      "ru3.node.check-host.net": [
        [
          0,
          3.00119495391846,
          "Connection timed out",
          null,
          null
        ]
      ],
      "ru4.node.check-host.net": [
        [
          0,
          9.85073900222778,
          "Connection reset by peer",
          null,
          "60.248.62.203"
        ]
      ],
      "se1.node.check-host.net": [
        [
          0,
          24.9994940757751,
          "Connection timed out",
          null,
          "60.248.62.203"
        ]
      ],
      "tr1.node.check-host.net": [
        [
          0,
          25.0010280609131,
          "Connection timed out",
          null,
          "60.248.62.203"
        ]
      ],
      "tr2.node.check-host.net": [
        [
          0,
          3.00154900550842,
          "Connection timed out",
          null,
          null
        ]
      ],
      "ua1.node.check-host.net": [
        [
          0,
          3.00185894966125,
          "Connection timed out",
          null,
          null
        ]
      ],
      "ua2.node.check-host.net": [
        [
          0,
          25.0006511211395,
          "Connection timed out",
          null,
          "60.248.62.203"
        ]
      ],
      "ua3.node.check-host.net": [
        [
          0,
          3.00370478630066,
          "Connection timed out",
          null,
          null
        ]
      ],
      "uk1.node.check-host.net": [
        [
          0,
          7.06808686256409,
          "Connection reset by peer",
          null,
          "60.248.62.203"
        ]
      ],
      "us1.node.check-host.net": [
        [
          0,
          1.90281796455383,
          "Connection reset by peer",
          null,
          "60.248.62.203"
        ]
      ],
      "us2.node.check-host.net": [
        [
          0,
          25.0003781318665,
          "Connection timed out",
          null,
          "60.248.62.203"
        ]
      ],
      "us3.node.check-host.net": [
        [
          0,
          25.0007889270782,
          "Connection timed out",
          null,
          "60.248.62.203"
        ]
      ],
      "vn1.node.check-host.net": [
        [
          0,
          3.0019679069519,
          "Connection timed out",
          null,
          null
        ]
      ]
    },
    "check_report_image": ""
  },
  "verified": true,
  "processed": true,
  "original_image": "https://example.com/default.png"
}