{
  "report_type": "ddos",
  "group_name": "NoName057(16)",
  "actor_name": "NoName057(16)",
  "operation_name": "Hack For Humanity",
  "network": "unknown",
  "targeted_website": "https://www.ljc.moj.gov.tw/",
  "targeted_org": "",
  "attack_type": "DDoS",
  "attacked_country": "TW",
  "attacker_country_affiliation": "unknown",
  "attack_date": "2025-03-19",
  "check_host": "24292616k71b",
  "additional_image": "",
  "check_details": {
    "website_verification": "https://www.ljc.moj.gov.tw/",
    "check_date": "2025-03-19",
    "check_results": {
      "bg1.node.check-host.net": [
        [
          0,
          3.00348901748657,
          "Connection timed out",
          null,
          null
        ]
      ],
      "br1.node.check-host.net": [
        [
          0,
          3.00135493278503,
          "Connection timed out",
          null,
          null
        ]
      ],
      "ch1.node.check-host.net": [
        [
          0,
          3.00139093399048,
          "Connection timed out",
          null,
          null
        ]
      ],
      "cz1.node.check-host.net": [
        [
          0,
          3.00209188461304,
          "Connection timed out",
          null,
          null
        ]
      ],
      "de1.node.check-host.net": [
        [
          0,
          3.00084686279297,
          "Connection timed out",
          null,
          null
        ]
      ],
      "de4.node.check-host.net": [
        [
          0,
          3.00169682502747,
          "Connection timed out",
          null,
          null
        ]
      ],
      "es1.node.check-host.net": [
        [
          0,
          3.00168800354004,
          "Connection timed out",
          null,
          null
        ]
      ],
      "fi1.node.check-host.net": [
        [
          0,
          3.00205302238464,
          "Connection timed out",
          null,
          null
        ]
      ],
      "fr1.node.check-host.net": [
        [
          0,
          3.00126099586487,
          "Connection timed out",
          null,
          null
        ]
      ],
      "fr2.node.check-host.net": [
        null,
        {
          "message": "Connect timeout"
        }
      ],
      "hk1.node.check-host.net": [
        [
          0,
          3.00185990333557,
          "Connection timed out",
          null,
          null
        ]
      ],
      "hu1.node.check-host.net": [
        [
          0,
          3.02055883407593,
          "Connection timed out",
          null,
          null
        ]
      ],
      "id2.node.check-host.net": [
        [
          0,
          3.00121307373047,
          "Connection timed out",
          null,
          null
        ]
      ],
      "il1.node.check-host.net": [
        [
          0,
          3.00153613090515,
          "Connection timed out",
          null,
          null
        ]
      ],
      "il2.node.check-host.net": [
        [
          0,
          3.0014431476593,
          "Connection timed out",
          null,
          null
        ]
      ],
      "in1.node.check-host.net": [
        [
          0,
          3.00227999687195,
          "Connection timed out",
          null,
          null
        ]
      ],
      "ir1.node.check-host.net": [
        [
          0,
          3.00114297866821,
          "Connection timed out",
          null,
          null
        ]
      ],
      "ir2.node.check-host.net": [
        [
          0,
          3.00256705284119,
          "Connection timed out",
          null,
          null
        ]
      ],
      "ir3.node.check-host.net": [
        [
          0,
          3.00359201431274,
          "Connection timed out",
          null,
          null
        ]
      ],
      "ir5.node.check-host.net": [
        [
          0,
          3.00208520889282,
          "Connection timed out",
          null,
          null
        ]
      ],
      "ir6.node.check-host.net": [
        [
          0,
          3.00182509422302,
          "Connection timed out",
          null,
          null
        ]
      ],
      "it2.node.check-host.net": [
        [
          0,
          3.00149989128113,
          "Connection timed out",
          null,
          null
        ]
      ],
      "jp1.node.check-host.net": [
        [
          0,
          3.00143194198608,
          "Connection timed out",
          null,
          null
        ]
      ],
      "kz1.node.check-host.net": [
        [
          0,
          3.07823204994202,
          "Connection timed out",
          null,
          null
        ]
      ],
      "lt1.node.check-host.net": [
        [
          0,
          3.00179219245911,
          "Connection timed out",
          null,
          null
        ]
      ],
      "md1.node.check-host.net": [
        [
          0,
          3.00262093544006,
          "Connection timed out",
          null,
          null
        ]
      ],
      "nl1.node.check-host.net": [
        [
          0,
          3.00167489051819,
          "Connection timed out",
          null,
          null
        ]
      ],
      "nl2.node.check-host.net": [
        [
          0,
          3.00147795677185,
          "Connection timed out",
          null,
          null
        ]
      ],
      "pl1.node.check-host.net": [
        [
          0,
          3.00148797035217,
          "Connection timed out",
          null,
          null
        ]
      ],
      "pl2.node.check-host.net": [
        [
          0,
          3.00146484375,
          "Connection timed out",
          null,
          null
        ]
      ],
      "pt1.node.check-host.net": [
        [
          0,
          3.00111317634583,
          "Connection timed out",
          null,
          null
        ]
      ],
      "rs1.node.check-host.net": [
        [
          0,
          3.00134992599487,
          "Connection timed out",
          null,
          null
        ]
      ],
      "ru1.node.check-host.net": [
        [
          0,
          3.0010039806366,
          "Connection timed out",
          null,
          null
        ]
      ],
      "ru2.node.check-host.net": [
        [
          0,
          3.31208801269531,
          "Connection timed out",
          null,
          null
        ]
      ],
      "ru3.node.check-host.net": [
        [
          0,
          3.00126004219055,
          "Connection timed out",
          null,
          null
        ]
      ],
      "ru4.node.check-host.net": [
        [
          0,
          3.00177001953125,
          "Connection timed out",
          null,
          null
        ]
      ],
      "se1.node.check-host.net": [
        [
          0,
          3.00175905227661,
          "Connection timed out",
          null,
          null
        ]
      ],
      "tr1.node.check-host.net": [
        [
          0,
          3.00188398361206,
          "Connection timed out",
          null,
          null
        ]
      ],
      "tr2.node.check-host.net": [
        [
          0,
          3.00161099433899,
          "Connection timed out",
          null,
          null
        ]
      ],
      "ua1.node.check-host.net": [
        [
          0,
          3.00169491767883,
          "Connection timed out",
          null,
          null
        ]
      ],
      "ua2.node.check-host.net": [
        [
          0,
          3.00107908248901,
          "Connection timed out",
          null,
          null
        ]
      ],
      "ua3.node.check-host.net": [
        [
          0,
          3.00253200531006,
          "Connection timed out",
          null,
          null
        ]
      ],
      "uk1.node.check-host.net": [
        [
          0,
          3.00315499305725,
          "Connection timed out",
          null,
          null
        ]
      ],
      "us1.node.check-host.net": [
        [
          0,
          3.0010449886322,
          "Connection timed out",
          null,
          null
        ]
      ],
      "us2.node.check-host.net": [
        [
          0,
          3.00058889389038,
          "Connection timed out",
          null,
          null
        ]
      ],
      "us3.node.check-host.net": [
        [
          0,
          3.00223088264465,
          "Connection timed out",
          null,
          null
        ]
      ],
      "vn1.node.check-host.net": [
        [
          0,
          3.00144505500793,
          "Connection timed out",
          null,
          null
        ]
      ]
    },
    "check_report_image": ""
  },
  "verified": true,
  "processed": true,
  "original_image": "https://example.com/default.png"
}